[
  {
    "inputs": [
      {
        "internalType": "uint256",
        "name": "_interestRate",
        "type": "uint256"
      }
    ],
    "stateMutability": "nonpayable",
    "type": "constructor"
  },
  {
    "anonymous": false,
    "inputs": [
      {
        "indexed": false,
        "internalType": "uint256",
        "name": "interest",
        "type": "uint256"
      }
    ],
    "name": "InterestCalculated",
    "type": "event"
  },
  {
    "inputs": [],
    "name": "calculateInterest",
    "outputs": [
      {
        "internalType": "uint256",
        "name": "",
        "type": "uint256"
      }
    ],
    "stateMutability": "nonpayable",
    "type": "function"
  },
  {
    "inputs": [],
    "name": "getInterestRate",
    "outputs": [
      {
        "internalType": "uint256",
        "name": "",
        "type": "uint256"
      }
    ],
    "stateMutability": "view",
    "type": "function"
  },
  {
    "inputs": [],
    "name": "getTotalBalance",
    "outputs": [
      {
        "internalType": "uint256",
        "name": "",
        "type": "uint256"
      }
    ],
    "stateMutability": "view",
    "type": "function"
  },
  {
    "inputs": [
      {
        "internalType": "uint256",
        "name": "_interestRate",
        "type": "uint256"
      }
    ],
    "name": "setInterestRate",
    "outputs": [],
    "stateMutability": "nonpayable",
    "type": "function"
  }
]
